Examples/AND.v
module AND (a,b,v);
input [2:1] a, b;
output [2:1] v;
	assign v[1] = a[1] & b[1];
	assign v[2] = a[2] & b[2];
endmodule

Examples/AND_tb.v
`include "AND.v"
module AND_tb;
reg [2:1]a;
reg [2:1]b;

wire [2:1]v;

initial begin
	$dumpfile("AND_tb.vcd");
	$dumpvars(0, AND_tb);
	$monitor($time, ": , a: %b, b: %b, v: %b", a, b, v);
end
AND AND_(.a(a), .b(b), .v(v));


initial begin
a = 2'b00; 
b = 2'b00; 

#10 a = 2'b10; b = 2'b00; 
#10 a = 2'b01; b = 2'b00; 
#10 a = 2'b11; b = 2'b00; 
#10 a = 2'b00; b = 2'b10; 
#10 a = 2'b10; b = 2'b10; 
#10 a = 2'b01; b = 2'b10; 
#10 a = 2'b11; b = 2'b10; 
#10 a = 2'b00; b = 2'b01; 
#10 a = 2'b10; b = 2'b01; 
#10 a = 2'b01; b = 2'b01; 
#10 a = 2'b11; b = 2'b01; 
#10 a = 2'b00; b = 2'b11; 
#10 a = 2'b10; b = 2'b11; 
#10 a = 2'b01; b = 2'b11; 
#10 a = 2'b11; b = 2'b11; 
#10 a = 2'b00; b = 2'b00; 

end
endmodule

Examples/AND_tb.vcd
$date
	Wed Sep 11 18:52:39 2019
$end
$version
	Icarus Verilog
$end
$timescale
	1s
$end
$scope module AND_tb $end
$var wire 2 ! v [2:1] $end
$var reg 2 " a [2:1] $end
$var reg 2 # b [2:1] $end
$scope module AND_ $end
$var wire 2 $ a [2:1] $end
$var wire 2 % b [2:1] $end
$var wire 2 & v [2:1] $end
$upscope $end
$upscope $end
$enddefinitions $end
#0
$dumpvars
b0 &
b0 %
b0 $
b0 #
b0 "
b0 !
$end
#10
b10 "
b10 $
#20
b1 "
b1 $
#30
b11 "
b11 $
#40
b10 #
b10 %
b0 "
b0 $
#50
b10 !
b10 &
b10 "
b10 $
#60
b0 !
b0 &
b1 "
b1 $
#70
b10 !
b10 &
b11 "
b11 $
#80
b0 !
b0 &
b1 #
b1 %
b0 "
b0 $
#90
b10 "
b10 $
#100
b1 !
b1 &
b1 "
b1 $
#110
b11 "
b11 $
#120
b0 !
b0 &
b11 #
b11 %
b0 "
b0 $
#130
b10 !
b10 &
b10 "
b10 $
#140
b1 !
b1 &
b1 "
b1 $
#150
b11 !
b11 &
b11 "
b11 $
#160
b0 !
b0 &
b0 #
b0 %
b0 "
b0 $
